{
	"configurations" : 
	[
		{
			"directories" : 
			[
				{
					"build" : ".",
					"jsonFile" : "directory-.-Debug-d0094a50bb2071803777.json",
					"minimumCMakeVersion" : 
					{
						"string" : "3.18"
					},
					"projectIndex" : 0,
					"source" : ".",
					"targetIndexes" : 
					[
						0,
						1,
						2,
						3,
						4,
						5,
						6,
						7,
						8,
						9
					]
				}
			],
			"name" : "Debug",
			"projects" : 
			[
				{
					"directoryIndexes" : 
					[
						0
					],
					"name" : "Samples_OpenGL",
					"targetIndexes" : 
					[
						0,
						1,
						2,
						3,
						4,
						5,
						6,
						7,
						8,
						9
					]
				}
			],
			"targets" : 
			[
				{
					"directoryIndex" : 0,
					"id" : "3D_scene::@6890427a1f51a3e7e1df",
					"jsonFile" : "target-3D_scene-Debug-a1e7614e528f22ccf277.json",
					"name" : "3D_scene",
					"projectIndex" : 0
				},
				{
					"directoryIndex" : 0,
					"id" : "Common::@6890427a1f51a3e7e1df",
					"jsonFile" : "target-Common-Debug-4499bfe0af996d9b7ae7.json",
					"name" : "Common",
					"projectIndex" : 0
				},
				{
					"directoryIndex" : 0,
					"id" : "data_target::@6890427a1f51a3e7e1df",
					"jsonFile" : "target-data_target-Debug-07d598875fd0a5b8c634.json",
					"name" : "data_target",
					"projectIndex" : 0
				},
				{
					"directoryIndex" : 0,
					"id" : "double_texture_triangle::@6890427a1f51a3e7e1df",
					"jsonFile" : "target-double_texture_triangle-Debug-7139a4155042e5d9d403.json",
					"name" : "double_texture_triangle",
					"projectIndex" : 0
				},
				{
					"directoryIndex" : 0,
					"id" : "empty_polygon::@6890427a1f51a3e7e1df",
					"jsonFile" : "target-empty_polygon-Debug-8e499c6592e16cd87276.json",
					"name" : "empty_polygon",
					"projectIndex" : 0
				},
				{
					"directoryIndex" : 0,
					"id" : "empty_square::@6890427a1f51a3e7e1df",
					"jsonFile" : "target-empty_square-Debug-f80d864cb731ebcac3ce.json",
					"name" : "empty_square",
					"projectIndex" : 0
				},
				{
					"directoryIndex" : 0,
					"id" : "empty_star::@6890427a1f51a3e7e1df",
					"jsonFile" : "target-empty_star-Debug-75d3656c8b33b3c6eea8.json",
					"name" : "empty_star",
					"projectIndex" : 0
				},
				{
					"directoryIndex" : 0,
					"id" : "full_square::@6890427a1f51a3e7e1df",
					"jsonFile" : "target-full_square-Debug-e86f544b8d8803f6bddd.json",
					"name" : "full_square",
					"projectIndex" : 0
				},
				{
					"directoryIndex" : 0,
					"id" : "full_star::@6890427a1f51a3e7e1df",
					"jsonFile" : "target-full_star-Debug-c3956d4d7e93e14ca498.json",
					"name" : "full_star",
					"projectIndex" : 0
				},
				{
					"directoryIndex" : 0,
					"id" : "shader_target::@6890427a1f51a3e7e1df",
					"jsonFile" : "target-shader_target-Debug-b2f50b47cd3151d8a3dc.json",
					"name" : "shader_target",
					"projectIndex" : 0
				}
			]
		}
	],
	"kind" : "codemodel",
	"paths" : 
	{
		"build" : "C:/Users/Mat/special_repo/git-hub_classroom_compute_graphic/samples-materfe/cmake-build-debug",
		"source" : "C:/Users/Mat/special_repo/git-hub_classroom_compute_graphic/samples-materfe"
	},
	"version" : 
	{
		"major" : 2,
		"minor" : 7
	}
}
